{
    "boxes": [
        {
            "id": "1",
            "type": "polygon",
            "label": "Outside",
            "x": "1200.3242",
            "y": "618.3506",
            "width": "1894.9300",
            "height": "1090.4473",
            "points": [
                [
                    983.501,
                    1001.512
                ],
                [
                    922.237,
                    974.343
                ],
                [
                    811.646,
                    925.295
                ],
                [
                    680.689,
                    866.797
                ],
                [
                    539.731,
                    804.475
                ],
                [
                    480.003,
                    778.043
                ],
                [
                    441.003,
                    758.673
                ],
                [
                    408.045,
                    742.12
                ],
                [
                    384.409,
                    729.48
                ],
                [
                    339.448,
                    703.7
                ],
                [
                    313.357,
                    688.332
                ],
                [
                    290.903,
                    673.34
                ],
                [
                    284.175,
                    667.338
                ],
                [
                    275.721,
                    657.881
                ],
                [
                    269.721,
                    649.292
                ],
                [
                    265.812,
                    642.29
                ],
                [
                    261.63,
                    633.106
                ],
                [
                    257.721,
                    624.558
                ],
                [
                    254.721,
                    612.918
                ],
                [
                    253.405,
                    606.237
                ],
                [
                    252.859,
                    598.235
                ],
                [
                    252.95,
                    581.321
                ],
                [
                    254.859,
                    568.641
                ],
                [
                    257.223,
                    560.912
                ],
                [
                    260.132,
                    551.367
                ],
                [
                    266.586,
                    538.462
                ],
                [
                    272.677,
                    529.186
                ],
                [
                    278.314,
                    522.821
                ],
                [
                    290.041,
                    511.193
                ],
                [
                    301.768,
                    502.735
                ],
                [
                    312.454,
                    497.107
                ],
                [
                    346.181,
                    478.92
                ],
                [
                    363.908,
                    468.553
                ],
                [
                    390.274,
                    450.827
                ],
                [
                    406.092,
                    438.915
                ],
                [
                    418.274,
                    429.366
                ],
                [
                    431.819,
                    417.999
                ],
                [
                    463.092,
                    387.724
                ],
                [
                    489.007,
                    355.375
                ],
                [
                    504.371,
                    338.37
                ],
                [
                    519.462,
                    323.456
                ],
                [
                    533.825,
                    310.725
                ],
                [
                    572.871,
                    273.679
                ],
                [
                    592.642,
                    254.727
                ],
                [
                    595.642,
                    249.362
                ],
                [
                    595.914,
                    242.815
                ],
                [
                    591.369,
                    237.45
                ],
                [
                    580.096,
                    226.633
                ],
                [
                    567.46,
                    215.903
                ],
                [
                    560.278,
                    208.781
                ],
                [
                    555.096,
                    202.052
                ],
                [
                    552.551,
                    194.231
                ],
                [
                    550.824,
                    186.865
                ],
                [
                    551.369,
                    175.815
                ],
                [
                    553.914,
                    166.904
                ],
                [
                    557.551,
                    160.134
                ],
                [
                    560.733,
                    155.86
                ],
                [
                    565.369,
                    150.586
                ],
                [
                    582.278,
                    132.265
                ],
                [
                    594.28,
                    120.811
                ],
                [
                    602.371,
                    114.627
                ],
                [
                    611.553,
                    108.444
                ],
                [
                    619.644,
                    102.806
                ],
                [
                    628.007,
                    97.986
                ],
                [
                    636.142,
                    93.315
                ],
                [
                    646.869,
                    88.677
                ],
                [
                    659.323,
                    83.585
                ],
                [
                    668.778,
                    79.947
                ],
                [
                    678.778,
                    77.31
                ],
                [
                    688.051,
                    74.946
                ],
                [
                    697.323,
                    73.309
                ],
                [
                    710.96,
                    73.127
                ],
                [
                    716.687,
                    74.491
                ],
                [
                    721.596,
                    76.037
                ],
                [
                    724.869,
                    76.946
                ],
                [
                    729.96,
                    80.493
                ],
                [
                    762.237,
                    101.863
                ],
                [
                    783.509,
                    115.594
                ],
                [
                    868.371,
                    171.508
                ],
                [
                    946.551,
                    222.333
                ],
                [
                    996.877,
                    254.775
                ],
                [
                    1027.422,
                    275.236
                ],
                [
                    1044.695,
                    286.239
                ],
                [
                    1061.24,
                    296.787
                ],
                [
                    1074.695,
                    305.881
                ],
                [
                    1114.286,
                    331.415
                ],
                [
                    1130.195,
                    341.963
                ],
                [
                    1150.304,
                    354.806
                ],
                [
                    1166.789,
                    365.689
                ],
                [
                    1173.933,
                    371.186
                ],
                [
                    1179.428,
                    376.133
                ],
                [
                    1183.384,
                    382.179
                ],
                [
                    1188.66,
                    390.315
                ],
                [
                    1191.187,
                    396.801
                ],
                [
                    1193.386,
                    403.177
                ],
                [
                    1195.808,
                    412.561
                ],
                [
                    1197.567,
                    423.445
                ],
                [
                    1199.655,
                    437.297
                ],
                [
                    1200.754,
                    456.645
                ],
                [
                    1200.095,
                    472.519
                ],
                [
                    1199.325,
                    486.371
                ],
                [
                    1198.336,
                    499.563
                ],
                [
                    1197.017,
                    514.184
                ],
                [
                    1193.171,
                    573.209
                ],
                [
                    1193.171,
                    584.199
                ],
                [
                    1194.709,
                    595.412
                ],
                [
                    1197.237,
                    608.715
                ],
                [
                    1200.367,
                    621.407
                ],
                [
                    1205.642,
                    634.38
                ],
                [
                    1210.698,
                    644.164
                ],
                [
                    1217.622,
                    655.927
                ],
                [
                    1224.875,
                    666.151
                ],
                [
                    1230.92,
                    673.297
                ],
                [
                    1239.932,
                    683.521
                ],
                [
                    1285.272,
                    731.478
                ],
                [
                    1336.979,
                    786.154
                ],
                [
                    1352.6,
                    803.06
                ],
                [
                    1357.216,
                    808.447
                ],
                [
                    1362.931,
                    813.504
                ],
                [
                    1366.777,
                    819.33
                ],
                [
                    1370.184,
                    825.487
                ],
                [
                    1372.382,
                    829.994
                ],
                [
                    1374.031,
                    835.051
                ],
                [
                    1375.02,
                    839.998
                ],
                [
                    1375.13,
                    848.683
                ],
                [
                    1373.262,
                    855.939
                ],
                [
                    1369.745,
                    863.415
                ],
                [
                    1366.448,
                    867.25
                ],
                [
                    1361.832,
                    872.087
                ],
                [
                    1355.897,
                    875.495
                ],
                [
                    1264.128,
                    912.213
                ],
                [
                    1256.11,
                    915.33
                ],
                [
                    1249.735,
                    918.628
                ],
                [
                    1245.779,
                    923.465
                ],
                [
                    1244.35,
                    928.962
                ],
                [
                    1244.46,
                    933.469
                ],
                [
                    1245.119,
                    937.427
                ],
                [
                    1247.647,
                    941.385
                ],
                [
                    1250.395,
                    944.023
                ],
                [
                    1254.681,
                    946.771
                ],
                [
                    1261.165,
                    948.97
                ],
                [
                    1267.43,
                    951.828
                ],
                [
                    1274.024,
                    953.697
                ],
                [
                    1279.739,
                    956.446
                ],
                [
                    1288.861,
                    958.974
                ],
                [
                    1297.653,
                    961.723
                ],
                [
                    1309.747,
                    964.507
                ],
                [
                    1318.1,
                    966.705
                ],
                [
                    1327.771,
                    968.904
                ],
                [
                    1339.091,
                    970.663
                ],
                [
                    1354.038,
                    972.532
                ],
                [
                    1365.248,
                    973.851
                ],
                [
                    1383.053,
                    974.401
                ],
                [
                    1396.459,
                    974.731
                ],
                [
                    1410.856,
                    974.071
                ],
                [
                    1422.616,
                    972.642
                ],
                [
                    1430.199,
                    970.993
                ],
                [
                    1435.914,
                    968.134
                ],
                [
                    1440.75,
                    963.957
                ],
                [
                    1446.025,
                    958.68
                ],
                [
                    1454.158,
                    947.467
                ],
                [
                    1510.531,
                    875.466
                ],
                [
                    1585.485,
                    779.298
                ],
                [
                    1666.759,
                    675.271
                ],
                [
                    1761.672,
                    553.393
                ],
                [
                    1848.665,
                    441.276
                ],
                [
                    1867.514,
                    417.659
                ],
                [
                    1871.58,
                    411.503
                ],
                [
                    1874.987,
                    403.917
                ],
                [
                    1877.405,
                    397.211
                ],
                [
                    1879.274,
                    390.175
                ],
                [
                    1880.373,
                    380.721
                ],
                [
                    1880.592,
                    370.005
                ],
                [
                    1879.164,
                    360.77
                ],
                [
                    1876.636,
                    350.549
                ],
                [
                    1872.35,
                    340.874
                ],
                [
                    1868.723,
                    333.953
                ],
                [
                    1864.986,
                    328.236
                ],
                [
                    1859.931,
                    324.058
                ],
                [
                    1854.985,
                    321.2
                ],
                [
                    1849.6,
                    319.111
                ],
                [
                    1843.115,
                    317.572
                ],
                [
                    1799.044,
                    316.802
                ],
                [
                    1767.12,
                    316.362
                ],
                [
                    1759.097,
                    315.263
                ],
                [
                    1751.294,
                    313.504
                ],
                [
                    1744.48,
                    310.865
                ],
                [
                    1737.996,
                    307.127
                ],
                [
                    1733.27,
                    304.379
                ],
                [
                    1728.049,
                    299.882
                ],
                [
                    1720.246,
                    292.187
                ],
                [
                    1716.29,
                    286.14
                ],
                [
                    1712.003,
                    278.665
                ],
                [
                    1709.915,
                    272.728
                ],
                [
                    1707.717,
                    265.912
                ],
                [
                    1706.288,
                    259.646
                ],
                [
                    1706.069,
                    241.898
                ],
                [
                    1708.596,
                    232.224
                ],
                [
                    1711.234,
                    223.381
                ],
                [
                    1715.41,
                    215.796
                ],
                [
                    1720.576,
                    208.87
                ],
                [
                    1725.412,
                    202.991
                ],
                [
                    1732.555,
                    197.164
                ],
                [
                    1741.567,
                    191.997
                ],
                [
                    1750.579,
                    188.149
                ],
                [
                    1760.471,
                    185.291
                ],
                [
                    1769.043,
                    184.522
                ],
                [
                    1777.506,
                    184.522
                ],
                [
                    1785.748,
                    185.621
                ],
                [
                    1792.352,
                    187.273
                ],
                [
                    1802.024,
                    191.011
                ],
                [
                    1916.323,
                    238.173
                ],
                [
                    1939.128,
                    247.845
                ],
                [
                    1948.25,
                    252.792
                ],
                [
                    1956.273,
                    257.74
                ],
                [
                    1967.153,
                    264.556
                ],
                [
                    1976.715,
                    272.581
                ],
                [
                    1984.738,
                    278.407
                ],
                [
                    1997.109,
                    287.959
                ],
                [
                    2003.154,
                    294.116
                ],
                [
                    2013.924,
                    304.559
                ],
                [
                    2020.738,
                    311.705
                ],
                [
                    2025.794,
                    317.422
                ],
                [
                    2033.267,
                    325.997
                ],
                [
                    2039.862,
                    334.132
                ],
                [
                    2047.173,
                    344.723
                ],
                [
                    2053.217,
                    354.288
                ],
                [
                    2057.284,
                    361.763
                ],
                [
                    2062.889,
                    372.757
                ],
                [
                    2065.417,
                    379.353
                ],
                [
                    2068.274,
                    388.478
                ],
                [
                    2071.022,
                    396.713
                ],
                [
                    2073.33,
                    405.728
                ],
                [
                    2075.857,
                    416.392
                ],
                [
                    2078.056,
                    428.155
                ],
                [
                    2079.814,
                    438.269
                ],
                [
                    2087.617,
                    480.86
                ],
                [
                    2099.824,
                    553.182
                ],
                [
                    2116.689,
                    655.836
                ],
                [
                    2134.161,
                    765.836
                ],
                [
                    2146.141,
                    844.13
                ],
                [
                    2147.24,
                    855.014
                ],
                [
                    2147.789,
                    862.599
                ],
                [
                    2147.679,
                    875.792
                ],
                [
                    2144.822,
                    888.214
                ],
                [
                    2142.793,
                    896.659
                ],
                [
                    2139.496,
                    906.223
                ],
                [
                    2135.76,
                    914.359
                ],
                [
                    2131.144,
                    920.955
                ],
                [
                    2126.308,
                    928.32
                ],
                [
                    2120.373,
                    934.917
                ],
                [
                    2115.098,
                    940.963
                ],
                [
                    2109.053,
                    945.91
                ],
                [
                    2102.239,
                    951.737
                ],
                [
                    2092.018,
                    958.223
                ],
                [
                    2082.127,
                    962.73
                ],
                [
                    2072.902,
                    966.835
                ],
                [
                    2061.472,
                    971.892
                ],
                [
                    2051.581,
                    976.51
                ],
                [
                    2042.239,
                    980.028
                ],
                [
                    2033.887,
                    983.326
                ],
                [
                    2022.677,
                    987.503
                ],
                [
                    1998.827,
                    996.18
                ],
                [
                    1981.133,
                    1002.226
                ],
                [
                    1965.197,
                    1007.393
                ],
                [
                    1948.272,
                    1012.56
                ],
                [
                    1914.974,
                    1021.846
                ],
                [
                    1892.883,
                    1026.903
                ],
                [
                    1876.947,
                    1030.641
                ],
                [
                    1845.238,
                    1036.841
                ],
                [
                    1822.268,
                    1040.689
                ],
                [
                    1792.532,
                    1044.645
                ],
                [
                    1759.341,
                    1048.713
                ],
                [
                    1715.867,
                    1053.593
                ],
                [
                    1663.723,
                    1059.529
                ],
                [
                    1633.719,
                    1063.487
                ],
                [
                    1612.178,
                    1066.345
                ],
                [
                    1598.001,
                    1070.413
                ],
                [
                    1584.373,
                    1075.03
                ],
                [
                    1573.547,
                    1079.808
                ],
                [
                    1562.007,
                    1086.404
                ],
                [
                    1551.017,
                    1093.879
                ],
                [
                    1536.509,
                    1103.993
                ],
                [
                    1521.782,
                    1114.657
                ],
                [
                    1511.452,
                    1120.044
                ],
                [
                    1502.22,
                    1123.012
                ],
                [
                    1493.318,
                    1124.771
                ],
                [
                    1482.982,
                    1125.431
                ],
                [
                    1467.595,
                    1123.342
                ],
                [
                    1451.549,
                    1119.165
                ],
                [
                    1420.115,
                    1110.26
                ],
                [
                    1373.578,
                    1097.177
                ],
                [
                    1359.29,
                    1095.528
                ],
                [
                    1348.74,
                    1094.429
                ],
                [
                    1335.551,
                    1094.539
                ],
                [
                    1323.682,
                    1096.078
                ],
                [
                    1315.109,
                    1098.277
                ],
                [
                    1305.878,
                    1101.575
                ],
                [
                    1296.978,
                    1106.957
                ],
                [
                    1287.636,
                    1113.664
                ],
                [
                    1277.854,
                    1122.458
                ],
                [
                    1266.534,
                    1132.243
                ],
                [
                    1256.533,
                    1141.367
                ],
                [
                    1246.862,
                    1149.063
                ],
                [
                    1236.751,
                    1155.109
                ],
                [
                    1228.948,
                    1158.627
                ],
                [
                    1220.375,
                    1160.936
                ],
                [
                    1210.923,
                    1162.915
                ],
                [
                    1203.835,
                    1163.574
                ],
                [
                    1185.701,
                    1163.354
                ],
                [
                    1168.446,
                    1158.407
                ],
                [
                    1159.763,
                    1154.45
                ],
                [
                    1150.034,
                    1148.843
                ],
                [
                    1140.803,
                    1141.367
                ],
                [
                    1130.801,
                    1130.704
                ],
                [
                    1122.559,
                    1120.37
                ],
                [
                    1104.867,
                    1095.691
                ],
                [
                    1089.59,
                    1072.275
                ],
                [
                    1077.501,
                    1056.114
                ],
                [
                    1066.677,
                    1045.633
                ],
                [
                    1057.775,
                    1038.597
                ],
                [
                    1048.873,
                    1032.33
                ],
                [
                    1038.322,
                    1025.844
                ]
            ]
        },
        {
            "id": "2",
            "type": "polygon",
            "label": "Inside",
            "x": "1201.0068",
            "y": "617.8122",
            "width": "1865.1187",
            "height": "1060.4036",
            "points": [
                [
                    918.374,
                    955.57
                ],
                [
                    872.955,
                    935.587
                ],
                [
                    832.972,
                    917.747
                ],
                [
                    802.482,
                    904.224
                ],
                [
                    649.084,
                    835.892
                ],
                [
                    505.046,
                    772.185
                ],
                [
                    478.727,
                    759.381
                ],
                [
                    465.42,
                    753.575
                ],
                [
                    449.456,
                    745.087
                ],
                [
                    429.896,
                    735.017
                ],
                [
                    417.815,
                    729.118
                ],
                [
                    407.892,
                    724.227
                ],
                [
                    400.701,
                    719.911
                ],
                [
                    390.489,
                    714.3
                ],
                [
                    380.853,
                    708.834
                ],
                [
                    364.808,
                    700.066
                ],
                [
                    356.035,
                    694.743
                ],
                [
                    346.542,
                    689.133
                ],
                [
                    338.344,
                    684.529
                ],
                [
                    328.133,
                    678.343
                ],
                [
                    322.956,
                    675.322
                ],
                [
                    312.744,
                    668.56
                ],
                [
                    302.183,
                    661.231
                ],
                [
                    295.423,
                    655.045
                ],
                [
                    290.028,
                    648.904
                ],
                [
                    285.824,
                    644.045
                ],
                [
                    282.648,
                    638.718
                ],
                [
                    278.444,
                    631.149
                ],
                [
                    274.24,
                    622.738
                ],
                [
                    271.717,
                    615.262
                ],
                [
                    269.475,
                    603.954
                ],
                [
                    268.634,
                    592.46
                ],
                [
                    268.447,
                    586.759
                ],
                [
                    269.569,
                    576.953
                ],
                [
                    271.53,
                    568.169
                ],
                [
                    273.773,
                    560.795
                ],
                [
                    277.042,
                    553.786
                ],
                [
                    281.433,
                    545.095
                ],
                [
                    285.544,
                    539.034
                ],
                [
                    290.122,
                    533.24
                ],
                [
                    296.101,
                    527.633
                ],
                [
                    303.294,
                    521.465
                ],
                [
                    312.588,
                    515.494
                ],
                [
                    323.799,
                    509.326
                ],
                [
                    334.449,
                    504.28
                ],
                [
                    343.044,
                    499.233
                ],
                [
                    352.386,
                    494
                ],
                [
                    367.196,
                    485.503
                ],
                [
                    378.594,
                    478.121
                ],
                [
                    389.338,
                    470.925
                ],
                [
                    398.587,
                    464.477
                ],
                [
                    423.066,
                    446.035
                ],
                [
                    434.65,
                    436.036
                ],
                [
                    440.816,
                    430.989
                ],
                [
                    451.373,
                    421.457
                ],
                [
                    491.363,
                    380.775
                ],
                [
                    504.162,
                    366.851
                ],
                [
                    511.916,
                    357.88
                ],
                [
                    523.496,
                    344.983
                ],
                [
                    533.399,
                    335.451
                ],
                [
                    542.181,
                    326.199
                ],
                [
                    547.693,
                    320.031
                ],
                [
                    580.347,
                    287.709
                ],
                [
                    587.073,
                    281.354
                ],
                [
                    600.148,
                    269.83
                ],
                [
                    606.595,
                    263.382
                ],
                [
                    609.117,
                    258.709
                ],
                [
                    610.705,
                    252.541
                ],
                [
                    611.546,
                    242.729
                ],
                [
                    608.743,
                    235.44
                ],
                [
                    605.193,
                    229.085
                ],
                [
                    600.522,
                    223.771
                ],
                [
                    595.29,
                    218.912
                ],
                [
                    589.124,
                    213.865
                ],
                [
                    582.958,
                    209.006
                ],
                [
                    579.315,
                    205.548
                ],
                [
                    574.177,
                    201.249
                ],
                [
                    570.533,
                    196.67
                ],
                [
                    568.478,
                    192.184
                ],
                [
                    567.076,
                    186.582
                ],
                [
                    566.983,
                    178.732
                ],
                [
                    568.571,
                    173.218
                ],
                [
                    572.682,
                    166.584
                ],
                [
                    576.979,
                    161.258
                ],
                [
                    582.304,
                    155.557
                ],
                [
                    587.114,
                    150.147
                ],
                [
                    607.387,
                    131.083
                ],
                [
                    619.251,
                    121.84
                ],
                [
                    628.5,
                    115.859
                ],
                [
                    639.805,
                    108.851
                ],
                [
                    649.427,
                    103.898
                ],
                [
                    658.022,
                    100.16
                ],
                [
                    670.826,
                    95.401
                ],
                [
                    684.839,
                    91.348
                ],
                [
                    693.808,
                    89.199
                ],
                [
                    703.15,
                    87.704
                ],
                [
                    709.877,
                    87.61
                ],
                [
                    714.548,
                    88.732
                ],
                [
                    719.78,
                    91.348
                ],
                [
                    727.253,
                    96.675
                ],
                [
                    771.165,
                    125.925
                ],
                [
                    793.516,
                    140.528
                ],
                [
                    807.249,
                    149.686
                ],
                [
                    821.449,
                    158.283
                ],
                [
                    836.677,
                    168.937
                ],
                [
                    906.697,
                    214.381
                ],
                [
                    1027.211,
                    293.251
                ],
                [
                    1142.264,
                    367.851
                ],
                [
                    1152.541,
                    374.579
                ],
                [
                    1158.427,
                    378.878
                ],
                [
                    1164.457,
                    384.651
                ],
                [
                    1168.754,
                    389.417
                ],
                [
                    1171.744,
                    394.183
                ],
                [
                    1174.827,
                    400.258
                ],
                [
                    1176.882,
                    405.491
                ],
                [
                    1178.47,
                    411.191
                ],
                [
                    1180.432,
                    420.012
                ],
                [
                    1181.74,
                    428.423
                ],
                [
                    1182.674,
                    437.581
                ],
                [
                    1183.889,
                    445.057
                ],
                [
                    1183.609,
                    472.251
                ],
                [
                    1180.339,
                    514.558
                ],
                [
                    1178.47,
                    541.192
                ],
                [
                    1176.695,
                    572.779
                ],
                [
                    1176.728,
                    584.254
                ],
                [
                    1178.596,
                    600.421
                ],
                [
                    1181.586,
                    614.626
                ],
                [
                    1183.734,
                    622.008
                ],
                [
                    1187.004,
                    631.447
                ],
                [
                    1189.153,
                    636.68
                ],
                [
                    1191.769,
                    643.676
                ],
                [
                    1198.589,
                    656.946
                ],
                [
                    1204.848,
                    666.852
                ],
                [
                    1211.575,
                    675.543
                ],
                [
                    1218.395,
                    683.486
                ],
                [
                    1225.121,
                    690.963
                ],
                [
                    1229.979,
                    696.57
                ],
                [
                    1236.145,
                    703.391
                ],
                [
                    1277.302,
                    747.714
                ],
                [
                    1324.191,
                    799.227
                ],
                [
                    1337.177,
                    813.244
                ],
                [
                    1346.706,
                    823.617
                ],
                [
                    1350.717,
                    828.73
                ],
                [
                    1354.361,
                    834.898
                ],
                [
                    1356.416,
                    839.197
                ],
                [
                    1356.977,
                    845.178
                ],
                [
                    1356.323,
                    849.757
                ],
                [
                    1353.24,
                    854.897
                ],
                [
                    1349.689,
                    858.541
                ],
                [
                    1343.71,
                    861.812
                ],
                [
                    1336.423,
                    864.522
                ],
                [
                    1300.549,
                    878.54
                ],
                [
                    1250.526,
                    898.138
                ],
                [
                    1245.762,
                    901.035
                ],
                [
                    1243.146,
                    902.904
                ],
                [
                    1238.568,
                    906.736
                ],
                [
                    1235.859,
                    909.913
                ],
                [
                    1232.589,
                    914.212
                ],
                [
                    1230.067,
                    918.791
                ],
                [
                    1228.011,
                    923.277
                ],
                [
                    1227.451,
                    928.043
                ],
                [
                    1227.171,
                    935.052
                ],
                [
                    1228.105,
                    941.033
                ],
                [
                    1230.534,
                    946.266
                ],
                [
                    1233.804,
                    951.257
                ],
                [
                    1238.101,
                    954.995
                ],
                [
                    1242.212,
                    958.453
                ],
                [
                    1247.443,
                    961.069
                ],
                [
                    1254.263,
                    963.779
                ],
                [
                    1266.502,
                    968.732
                ],
                [
                    1278.367,
                    972.564
                ],
                [
                    1291.259,
                    976.582
                ],
                [
                    1302.192,
                    979.278
                ],
                [
                    1309.198,
                    980.96
                ],
                [
                    1316.953,
                    982.642
                ],
                [
                    1326.482,
                    984.605
                ],
                [
                    1336.198,
                    986.287
                ],
                [
                    1346.661,
                    987.688
                ],
                [
                    1355.723,
                    988.903
                ],
                [
                    1363.384,
                    989.464
                ],
                [
                    1372.633,
                    990.212
                ],
                [
                    1380.574,
                    990.399
                ],
                [
                    1411.173,
                    990.212
                ],
                [
                    1420.702,
                    989.277
                ],
                [
                    1428.643,
                    988.249
                ],
                [
                    1435.556,
                    986.193
                ],
                [
                    1441.815,
                    982.922
                ],
                [
                    1448.729,
                    978.343
                ],
                [
                    1454.988,
                    972.362
                ],
                [
                    1459.846,
                    966.288
                ],
                [
                    1465.732,
                    958.532
                ],
                [
                    1473.673,
                    948.813
                ],
                [
                    1498.43,
                    916.352
                ],
                [
                    1534.772,
                    870.187
                ],
                [
                    1591.48,
                    797.41
                ],
                [
                    1662.675,
                    706.461
                ],
                [
                    1740.591,
                    606.312
                ],
                [
                    1816.589,
                    509.149
                ],
                [
                    1881.206,
                    425.769
                ],
                [
                    1885.41,
                    418.199
                ],
                [
                    1889.801,
                    409.101
                ],
                [
                    1892.697,
                    400.316
                ],
                [
                    1894.566,
                    391.719
                ],
                [
                    1895.5,
                    384.718
                ],
                [
                    1896.06,
                    366.266
                ],
                [
                    1894.566,
                    357.948
                ],
                [
                    1893.071,
                    351.22
                ],
                [
                    1890.362,
                    343.379
                ],
                [
                    1886.344,
                    333.754
                ],
                [
                    1883.168,
                    327.025
                ],
                [
                    1876.909,
                    318.442
                ],
                [
                    1870.182,
                    312.368
                ],
                [
                    1864.016,
                    307.882
                ],
                [
                    1858.037,
                    304.798
                ],
                [
                    1849.535,
                    302.839
                ],
                [
                    1843.65,
                    302.092
                ],
                [
                    1760.223,
                    299.475
                ],
                [
                    1753.882,
                    297.218
                ],
                [
                    1749.337,
                    295.036
                ],
                [
                    1744.337,
                    291.671
                ],
                [
                    1738.791,
                    287.579
                ],
                [
                    1734.064,
                    282.487
                ],
                [
                    1730.7,
                    277.849
                ],
                [
                    1727.882,
                    272.848
                ],
                [
                    1725.155,
                    266.391
                ],
                [
                    1723.791,
                    260.117
                ],
                [
                    1722.428,
                    252.751
                ],
                [
                    1722.337,
                    246.168
                ],
                [
                    1723.61,
                    240.439
                ],
                [
                    1725.61,
                    233.582
                ],
                [
                    1727.882,
                    228.216
                ],
                [
                    1731.791,
                    222.397
                ],
                [
                    1736.246,
                    217.031
                ],
                [
                    1740.609,
                    212.265
                ],
                [
                    1745.519,
                    208.809
                ],
                [
                    1751.609,
                    205.626
                ],
                [
                    1758.246,
                    203.353
                ],
                [
                    1763.882,
                    201.989
                ],
                [
                    1769.791,
                    201.352
                ],
                [
                    1777.518,
                    201.352
                ],
                [
                    1783.246,
                    202.444
                ],
                [
                    1803.973,
                    209.446
                ],
                [
                    1859.7,
                    231.907
                ],
                [
                    1924.837,
                    257.278
                ],
                [
                    1932.382,
                    261.643
                ],
                [
                    1939.2,
                    265.826
                ],
                [
                    1947.291,
                    270.736
                ],
                [
                    1955.928,
                    276.267
                ],
                [
                    1963.291,
                    281.723
                ],
                [
                    1970.837,
                    287.361
                ],
                [
                    1982.018,
                    296.818
                ],
                [
                    1993.564,
                    307.276
                ],
                [
                    2005.109,
                    317.915
                ],
                [
                    2015.109,
                    329.191
                ],
                [
                    2023.2,
                    338.83
                ],
                [
                    2030.38,
                    347.995
                ],
                [
                    2034.744,
                    354.269
                ],
                [
                    2038.198,
                    359.726
                ],
                [
                    2043.835,
                    369.638
                ],
                [
                    2047.835,
                    379.186
                ],
                [
                    2051.198,
                    387.006
                ],
                [
                    2055.016,
                    398.737
                ],
                [
                    2057.696,
                    407.678
                ],
                [
                    2060.696,
                    419.681
                ],
                [
                    2065.787,
                    444.234
                ],
                [
                    2078.696,
                    513.288
                ],
                [
                    2093.696,
                    593.653
                ],
                [
                    2105.013,
                    659.287
                ],
                [
                    2112.831,
                    712.336
                ],
                [
                    2130.962,
                    832.275
                ],
                [
                    2132.807,
                    853.106
                ],
                [
                    2133.566,
                    864.713
                ],
                [
                    2132.481,
                    871.768
                ],
                [
                    2131.288,
                    878.931
                ],
                [
                    2128.032,
                    891.938
                ],
                [
                    2123.584,
                    901.598
                ],
                [
                    2118.159,
                    912.56
                ],
                [
                    2111.431,
                    921.134
                ],
                [
                    2104.487,
                    929.1
                ],
                [
                    2099.821,
                    933.55
                ],
                [
                    2093.311,
                    938.759
                ],
                [
                    2089.188,
                    941.69
                ],
                [
                    2079.857,
                    945.923
                ],
                [
                    2074.865,
                    948.796
                ],
                [
                    2066.836,
                    952.92
                ],
                [
                    2058.59,
                    956.177
                ],
                [
                    2048.933,
                    960.301
                ],
                [
                    2037.757,
                    964.968
                ],
                [
                    2005.206,
                    977.341
                ],
                [
                    1989.312,
                    982.922
                ],
                [
                    1968.588,
                    989.868
                ],
                [
                    1941.462,
                    998.66
                ],
                [
                    1891.009,
                    1011.567
                ],
                [
                    1855.529,
                    1019.273
                ],
                [
                    1828.62,
                    1024.374
                ],
                [
                    1800.3,
                    1027.847
                ],
                [
                    1753.322,
                    1033.925
                ],
                [
                    1737.204,
                    1035.771
                ],
                [
                    1690.222,
                    1041.632
                ],
                [
                    1615.401,
                    1049.881
                ],
                [
                    1605.202,
                    1051.726
                ],
                [
                    1594.299,
                    1054.588
                ],
                [
                    1584.534,
                    1057.953
                ],
                [
                    1573.901,
                    1062.403
                ],
                [
                    1559.686,
                    1069.675
                ],
                [
                    1545.038,
                    1079.118
                ],
                [
                    1534.837,
                    1085.787
                ],
                [
                    1522.901,
                    1094.904
                ],
                [
                    1512.485,
                    1102.61
                ],
                [
                    1506.514,
                    1106.133
                ],
                [
                    1495.339,
                    1108.629
                ],
                [
                    1489.588,
                    1109.714
                ],
                [
                    1477.11,
                    1109.172
                ],
                [
                    1469.081,
                    1108.195
                ],
                [
                    1463.004,
                    1105.807
                ],
                [
                    1456.169,
                    1103.528
                ],
                [
                    1418.183,
                    1093.325
                ],
                [
                    1389.433,
                    1084.313
                ],
                [
                    1376.521,
                    1081.599
                ],
                [
                    1366.105,
                    1079.971
                ],
                [
                    1356.014,
                    1078.886
                ],
                [
                    1349.07,
                    1078.018
                ],
                [
                    1332.304,
                    1078.018
                ],
                [
                    1324.383,
                    1079.212
                ],
                [
                    1310.494,
                    1082.468
                ],
                [
                    1296.389,
                    1088.329
                ],
                [
                    1288.904,
                    1092.506
                ],
                [
                    1279.898,
                    1099.126
                ],
                [
                    1256.678,
                    1120.616
                ],
                [
                    1239.308,
                    1135.749
                ],
                [
                    1230.302,
                    1140.851
                ],
                [
                    1221.513,
                    1144.758
                ],
                [
                    1211.531,
                    1147.363
                ],
                [
                    1195.475,
                    1148.014
                ],
                [
                    1185.384,
                    1147.146
                ],
                [
                    1175.293,
                    1144.324
                ],
                [
                    1165.528,
                    1139.548
                ],
                [
                    1156.246,
                    1133.036
                ],
                [
                    1149.193,
                    1126.524
                ],
                [
                    1139.536,
                    1114.693
                ],
                [
                    1124.994,
                    1095.716
                ],
                [
                    1097.325,
                    1055.232
                ],
                [
                    1086.366,
                    1042.317
                ],
                [
                    1067.329,
                    1024.412
                ],
                [
                    1055.61,
                    1016.923
                ],
                [
                    1050.022,
                    1013.894
                ],
                [
                    1041.667,
                    1010.204
                ],
                [
                    1030.6,
                    1005.645
                ],
                [
                    1019.207,
                    1000.652
                ],
                [
                    1006.946,
                    995.334
                ],
                [
                    987.307,
                    986.326
                ],
                [
                    975.48,
                    981.55
                ]
            ]
        }
    ],
    "height": 1440,
    "key": "Silverstone.png",
    "width": 2560
}